_morfeusz2.pyd
morfeusz2.dll
morfeusz2.py
morfeusz2-1.99.12.dist-info/METADATA
morfeusz2-1.99.12.dist-info/WHEEL
morfeusz2-1.99.12.dist-info/top_level.txt
morfeusz2-1.99.12.dist-info/RECORD
