Metadata-Version: 2.1
Name: morfeusz2
Version: 1.99.12
Summary: Python bindings for Morfeusz 2
Home-page: http://morfeusz.sgjp.pl
Author: Morfeusz SGJP Team
Author-email: morfeusz@ipipan.waw.pl
License: http://morfeusz.sgjp.pl/doc/license/
